mixedvines/__init__.py
mixedvines/_utils.py
mixedvines/copula.py
mixedvines/marginal.py
mixedvines/mixedvine.py
mixedvines-1.3.4.dist-info/LICENSE
mixedvines-1.3.4.dist-info/WHEEL
mixedvines-1.3.4.dist-info/METADATA
mixedvines-1.3.4.dist-info/RECORD
