Metadata-Version: 2.1
Name: mixedvines
Version: 1.3.4
Summary: Canonical vine copula trees with mixed marginals
Keywords: copula,mixed,vine,continuous,discrete,entropy
Author-email: Arno Onken <asnelt@asnelt.org>
Requires-Python: >=3.10
Classifier: Development Status :: 5 - Production/Stable
Classifier: Intended Audience :: Science/Research
Classifier: License :: OSI Approved :: GNU General Public License v3 (GPLv3)
Classifier: Operating System :: OS Independent
Classifier: Programming Language :: Python :: 3
Classifier: Topic :: Scientific/Engineering
Requires-Dist: numpy
Requires-Dist: scipy
Requires-Dist: sphinx ; extra == "docs"
Requires-Dist: numpydoc ; extra == "docs"
Project-URL: Bug Tracker, https://github.com/asnelt/mixedvines/issues
Project-URL: Documentation, https://mixedvines.readthedocs.io
Project-URL: Homepage, https://github.com/asnelt/mixedvines
Provides-Extra: docs
